odm/__init__.py
odm/api.py
odm/caching.py
odm/definition_importer.py
odm/enums.py
odm/filter_datatype_visitor.py
odm/filter_polars_dataframe_visitor.py
odm/filter_visitor.py
odm/logger.py
odm/models_caching.py
odm/models_definition.py
odm/models_query.py
odm/query.py
odm/query_utils.py
odm/settings.py
odm/utils.py
tip_odm-0.0.19.dist-info/METADATA
tip_odm-0.0.19.dist-info/WHEEL
tip_odm-0.0.19.dist-info/top_level.txt
tip_odm-0.0.19.dist-info/RECORD
